{"mean":{"confidence_interval":{"confidence_level":0.95,"lower_bound":8750.004008444437,"upper_bound":8795.795481482071},"point_estimate":8770.438054778353,"standard_error":11.656497442381854},"median":{"confidence_interval":{"confidence_level":0.95,"lower_bound":8765.051124559413,"upper_bound":8770.842222603327},"point_estimate":8766.440462851808,"standard_error":1.485704901379009},"median_abs_dev":{"confidence_interval":{"confidence_level":0.95,"lower_bound":7.585730868954393,"upper_bound":14.253347536569812},"point_estimate":9.320626041955677,"standard_error":1.7743370958022195},"slope":{"confidence_interval":{"confidence_level":0.95,"lower_bound":8725.13807442321,"upper_bound":8769.58102486634},"point_estimate":8749.844985812266,"standard_error":11.283433519316556},"std_dev":{"confidence_interval":{"confidence_level":0.95,"lower_bound":35.01260128349923,"upper_bound":187.61034759041127},"point_estimate":117.19032570505823,"standard_error":41.88645578633923}}