{"mean":{"confidence_interval":{"confidence_level":0.95,"lower_bound":73444.03940476428,"upper_bound":73511.14186125118},"point_estimate":73476.82581324723,"standard_error":17.10325114470974},"median":{"confidence_interval":{"confidence_level":0.95,"lower_bound":73420.60989010989,"upper_bound":73497.33797909407},"point_estimate":73462.5955882353,"standard_error":22.517595317258696},"median_abs_dev":{"confidence_interval":{"confidence_level":0.95,"lower_bound":123.05305834752431,"upper_bound":194.1574661311038},"point_estimate":159.77804640923395,"standard_error":19.15887838547233},"slope":{"confidence_interval":{"confidence_level":0.95,"lower_bound":73445.46263196862,"upper_bound":73556.06510466528},"point_estimate":73498.16115117482,"standard_error":28.145359680060828},"std_dev":{"confidence_interval":{"confidence_level":0.95,"lower_bound":139.29166483254497,"upper_bound":205.85061546088951},"point_estimate":171.9764380215655,"standard_error":17.16915819865259}}