{"mean":{"confidence_interval":{"confidence_level":0.95,"lower_bound":913.5609142545926,"upper_bound":920.2888135099171},"point_estimate":916.923940051729,"standard_error":1.7212140181024804},"median":{"confidence_interval":{"confidence_level":0.95,"lower_bound":912.1347672261294,"upper_bound":922.7858756150681},"point_estimate":916.730767385324,"standard_error":2.5095058469903146},"median_abs_dev":{"confidence_interval":{"confidence_level":0.95,"lower_bound":13.099382934089371,"upper_bound":21.416262302628827},"point_estimate":18.08978625164694,"standard_error":2.182143116704943},"slope":{"confidence_interval":{"confidence_level":0.95,"lower_bound":906.1133732211262,"upper_bound":913.199057754196},"point_estimate":909.7030269591078,"standard_error":1.8146450180097866},"std_dev":{"confidence_interval":{"confidence_level":0.95,"lower_bound":14.58570806333389,"upper_bound":19.926538775227282},"point_estimate":17.33760537913458,"standard_error":1.3572546979685045}}