{"mean":{"confidence_interval":{"confidence_level":0.95,"lower_bound":88945.75189572219,"upper_bound":89301.07274180837},"point_estimate":89077.14240189081,"standard_error":100.49378616640693},"median":{"confidence_interval":{"confidence_level":0.95,"lower_bound":88886.80361276455,"upper_bound":88968.40151515152},"point_estimate":88906.23363995296,"standard_error":21.76321740245442},"median_abs_dev":{"confidence_interval":{"confidence_level":0.95,"lower_bound":107.81983672218314,"upper_bound":184.45023002597003},"point_estimate":154.48561815084634,"standard_error":19.6747467778052},"slope":{"confidence_interval":{"confidence_level":0.95,"lower_bound":88935.67785044436,"upper_bound":89001.25101460247},"point_estimate":88967.55067779912,"standard_error":16.715973666243627},"std_dev":{"confidence_interval":{"confidence_level":0.95,"lower_bound":177.1692858380637,"upper_bound":1706.7445605538098},"point_estimate":1010.7606189545962,"standard_error":528.2892197515234}}