{"mean":{"confidence_interval":{"confidence_level":0.95,"lower_bound":16268.834440538869,"upper_bound":16295.50189109291},"point_estimate":16281.900531289444,"standard_error":6.792436838736697},"median":{"confidence_interval":{"confidence_level":0.95,"lower_bound":16262.24724536415,"upper_bound":16295.04572871848},"point_estimate":16285.269115573014,"standard_error":7.6205598034108615},"median_abs_dev":{"confidence_interval":{"confidence_level":0.95,"lower_bound":51.73836760563329,"upper_bound":78.76856972549594},"point_estimate":69.04385073834655,"standard_error":6.67753555877048},"slope":{"confidence_interval":{"confidence_level":0.95,"lower_bound":16253.461063975883,"upper_bound":16284.74016459645},"point_estimate":16269.49675169034,"standard_error":7.955859512683341},"std_dev":{"confidence_interval":{"confidence_level":0.95,"lower_bound":55.585470275064395,"upper_bound":82.19511324698748},"point_estimate":68.52330767860838,"standard_error":6.90020279376462}}