{"mean":{"confidence_interval":{"confidence_level":0.95,"lower_bound":2381648.3424431835,"upper_bound":2386403.175136364},"point_estimate":2383430.491818181,"standard_error":1315.215671000503},"median":{"confidence_interval":{"confidence_level":0.95,"lower_bound":2380505.590909091,"upper_bound":2382305.5454545454},"point_estimate":2381649.75,"standard_error":494.9070067823459},"median_abs_dev":{"confidence_interval":{"confidence_level":0.95,"lower_bound":2276.0268277740447,"upper_bound":4205.260043522963},"point_estimate":3034.174541587148,"standard_error":508.0244497864983},"slope":null,"std_dev":{"confidence_interval":{"confidence_level":0.95,"lower_bound":2977.553344405495,"upper_bound":22143.92172836346},"point_estimate":13204.964155503212,"standard_error":6593.613185213767}}