{"mean":{"confidence_interval":{"confidence_level":0.95,"lower_bound":72418.684825692,"upper_bound":72480.31182649564},"point_estimate":72448.58624342593,"standard_error":15.742768691824704},"median":{"confidence_interval":{"confidence_level":0.95,"lower_bound":72368.21428571429,"upper_bound":72483.19581280788},"point_estimate":72438.21472789116,"standard_error":28.51629101325118},"median_abs_dev":{"confidence_interval":{"confidence_level":0.95,"lower_bound":120.79911262119255,"upper_bound":187.6030661239227},"point_estimate":152.39056176821285,"standard_error":15.744419192124889},"slope":{"confidence_interval":{"confidence_level":0.95,"lower_bound":72430.94329576395,"upper_bound":72527.69785102938},"point_estimate":72477.07971352573,"standard_error":24.74833748773521},"std_dev":{"confidence_interval":{"confidence_level":0.95,"lower_bound":125.92745386784748,"upper_bound":189.75825443709428},"point_estimate":158.5537918369159,"standard_error":16.344241352389286}}