{"mean":{"confidence_interval":{"confidence_level":0.95,"lower_bound":73078.63321809041,"upper_bound":73333.7683346061},"point_estimate":73195.27448387838,"standard_error":65.2242316908737},"median":{"confidence_interval":{"confidence_level":0.95,"lower_bound":72979.07969854609,"upper_bound":73161.96734693878},"point_estimate":73075.31654761905,"standard_error":49.429018562785025},"median_abs_dev":{"confidence_interval":{"confidence_level":0.95,"lower_bound":252.6595865053777,"upper_bound":463.84782864631006},"point_estimate":322.6598379236783,"standard_error":54.412332845247136},"slope":{"confidence_interval":{"confidence_level":0.95,"lower_bound":73070.59045772573,"upper_bound":73228.27728934736},"point_estimate":73147.80382781988,"standard_error":40.25495539174823},"std_dev":{"confidence_interval":{"confidence_level":0.95,"lower_bound":406.490879372431,"upper_bound":922.8464641519013},"point_estimate":656.12566828248,"standard_error":142.54363998637282}}