{"mean":{"confidence_interval":{"confidence_level":0.95,"lower_bound":57635.06640493966,"upper_bound":57723.180977724034},"point_estimate":57667.99905805118,"standard_error":24.419919398835788},"median":{"confidence_interval":{"confidence_level":0.95,"lower_bound":57627.92307692308,"upper_bound":57651.51882141802},"point_estimate":57640.82130673231,"standard_error":6.01857898379878},"median_abs_dev":{"confidence_interval":{"confidence_level":0.95,"lower_bound":33.1185607608862,"upper_bound":59.72225156913537},"point_estimate":46.82882134526352,"standard_error":7.0150790941308845},"slope":{"confidence_interval":{"confidence_level":0.95,"lower_bound":57640.26371687473,"upper_bound":57660.173763664476},"point_estimate":57650.55585439141,"standard_error":5.055549036983905},"std_dev":{"confidence_interval":{"confidence_level":0.95,"lower_bound":48.97692924766949,"upper_bound":412.8416956748452},"point_estimate":245.65325115474235,"standard_error":123.84770732977205}}