{"mean":{"confidence_interval":{"confidence_level":0.95,"lower_bound":66908.98608375607,"upper_bound":67154.40269884127},"point_estimate":67002.02046265214,"standard_error":66.38080516499687},"median":{"confidence_interval":{"confidence_level":0.95,"lower_bound":66905.15,"upper_bound":66954.46233918128},"point_estimate":66932.33437908496,"standard_error":12.753054772427674},"median_abs_dev":{"confidence_interval":{"confidence_level":0.95,"lower_bound":110.81012905776034,"upper_bound":213.31198860983108},"point_estimate":180.9640372438435,"standard_error":27.95410290934619},"slope":{"confidence_interval":{"confidence_level":0.95,"lower_bound":66912.00913041699,"upper_bound":66973.69020305775},"point_estimate":66942.74054184523,"standard_error":15.719742396098434},"std_dev":{"confidence_interval":{"confidence_level":0.95,"lower_bound":171.97499081637474,"upper_bound":1107.4149679262741},"point_estimate":663.3961262860406,"standard_error":320.1820190512059}}