{"mean":{"confidence_interval":{"confidence_level":0.95,"lower_bound":25202.244276140525,"upper_bound":25268.03229440948},"point_estimate":25229.71659051031,"standard_error":17.10235716511896},"median":{"confidence_interval":{"confidence_level":0.95,"lower_bound":25188.761303191488,"upper_bound":25214.81979774365},"point_estimate":25204.429078014182,"standard_error":5.925302056463386},"median_abs_dev":{"confidence_interval":{"confidence_level":0.95,"lower_bound":23.263564109402203,"upper_bound":48.3434466249089},"point_estimate":32.5708681717515,"standard_error":6.193829926290093},"slope":{"confidence_interval":{"confidence_level":0.95,"lower_bound":25208.423302842548,"upper_bound":25275.389556453873},"point_estimate":25236.556277525124,"standard_error":17.718124669212603},"std_dev":{"confidence_interval":{"confidence_level":0.95,"lower_bound":41.36309236012591,"upper_bound":189.88868354041048},"point_estimate":121.4020366947556,"standard_error":43.45138737143579}}