{"mean":{"confidence_interval":{"confidence_level":0.95,"lower_bound":57222.47429507258,"upper_bound":57243.41780307312},"point_estimate":57232.642068682006,"standard_error":5.332313129688666},"median":{"confidence_interval":{"confidence_level":0.95,"lower_bound":57208.918130856764,"upper_bound":57230.491696478675},"point_estimate":57225.39738092586,"standard_error":6.8890651995426255},"median_abs_dev":{"confidence_interval":{"confidence_level":0.95,"lower_bound":32.494227359703025,"upper_bound":59.003397979346595},"point_estimate":49.0289427750471,"standard_error":6.734106412040201},"slope":{"confidence_interval":{"confidence_level":0.95,"lower_bound":57225.00353936759,"upper_bound":57251.81834413543},"point_estimate":57238.30245340952,"standard_error":6.840700260105727},"std_dev":{"confidence_interval":{"confidence_level":0.95,"lower_bound":43.565426794736304,"upper_bound":62.980669216288405},"point_estimate":53.75809305781677,"standard_error":4.948459637810773}}