{"mean":{"confidence_interval":{"confidence_level":0.95,"lower_bound":578.4708296975203,"upper_bound":587.8457981941241},"point_estimate":582.7610023938753,"standard_error":2.3993769945869254},"median":{"confidence_interval":{"confidence_level":0.95,"lower_bound":574.0647248869228,"upper_bound":579.1723167155425},"point_estimate":576.1612154721329,"standard_error":1.120174121473667},"median_abs_dev":{"confidence_interval":{"confidence_level":0.95,"lower_bound":7.266763668643152,"upper_bound":13.05135872107117},"point_estimate":10.42380760895999,"standard_error":1.4462697515782925},"slope":{"confidence_interval":{"confidence_level":0.95,"lower_bound":573.5763550552172,"upper_bound":577.9277842896793},"point_estimate":575.6199870841201,"standard_error":1.1089496084330888},"std_dev":{"confidence_interval":{"confidence_level":0.95,"lower_bound":13.895695595565106,"upper_bound":32.9591535100561},"point_estimate":24.110271227834176,"standard_error":4.860571542464667}}