{"mean":{"confidence_interval":{"confidence_level":0.95,"lower_bound":85565.04991439547,"upper_bound":85861.96550355587},"point_estimate":85680.42546339227,"standard_error":79.38041881994647},"median":{"confidence_interval":{"confidence_level":0.95,"lower_bound":85538.7045779271,"upper_bound":85599.58333333333},"point_estimate":85562.04224447868,"standard_error":18.413880433523275},"median_abs_dev":{"confidence_interval":{"confidence_level":0.95,"lower_bound":88.88593129371546,"upper_bound":155.97346826808047},"point_estimate":115.63921672062145,"standard_error":16.898315660579286},"slope":{"confidence_interval":{"confidence_level":0.95,"lower_bound":85593.57927218493,"upper_bound":86213.2027278375},"point_estimate":85806.83195803163,"standard_error":178.16226804524354},"std_dev":{"confidence_interval":{"confidence_level":0.95,"lower_bound":145.04049846121586,"upper_bound":1321.4499914400405},"point_estimate":799.0206944960621,"standard_error":360.3679122441049}}