{"mean":{"confidence_interval":{"confidence_level":0.95,"lower_bound":84224.6107481874,"upper_bound":84900.60053998762},"point_estimate":84514.4525088231,"standard_error":173.37605859886557},"median":{"confidence_interval":{"confidence_level":0.95,"lower_bound":84155.62846412847,"upper_bound":84288.25946969698},"point_estimate":84238.28483201581,"standard_error":35.1105127077901},"median_abs_dev":{"confidence_interval":{"confidence_level":0.95,"lower_bound":187.1056855670946,"upper_bound":309.74773067109686},"point_estimate":251.14787093856884,"standard_error":32.626187767071904},"slope":{"confidence_interval":{"confidence_level":0.95,"lower_bound":84193.55478806986,"upper_bound":84284.38450377517},"point_estimate":84238.26845845033,"standard_error":23.15798007316204},"std_dev":{"confidence_interval":{"confidence_level":0.95,"lower_bound":312.5832436351155,"upper_bound":2644.726640390107},"point_estimate":1733.5477320673397,"standard_error":558.189276492028}}